LICENSE
MANIFEST.in
README.md
setup.py
crypto_sqlite_browser/main.py
crypto_sqlite_browser.egg-info/PKG-INFO
crypto_sqlite_browser.egg-info/SOURCES.txt
crypto_sqlite_browser.egg-info/dependency_links.txt
crypto_sqlite_browser.egg-info/entry_points.txt
crypto_sqlite_browser.egg-info/requires.txt
crypto_sqlite_browser.egg-info/top_level.txt