Metadata-Version: 2.1
Name: crypto-sqlite-browser
Version: 1.0.1
Summary: A tool for encrypting and decrypting SQLite databases and browsing it securely
Author: Crypt00o
Author-email: 0xCrypt00o@protonmail.com
License-File: LICENSE
